[
	{
		"id": "1764114820009",
		"title": "Producto prueba",
		"description": "Producto para pruebas",
		"code": "P001",
		"price": 99.9,
		"status": true,
		"stock": 20,
		"category": "test",
		"thumbnails": [
			"/img/1.jpg"
		]
	},
	{
		"id": "1764114835486",
		"title": "Producto prueba",
		"description": "Producto para pruebas",
		"code": "P001",
		"price": 99.9,
		"status": true,
		"stock": 20,
		"category": "test",
		"thumbnails": [
			"/img/1.jpg"
		]
	},
	{
		"id": "1764115133542",
		"title": "Producto prueba",
		"description": "Producto para pruebas",
		"code": "P001",
		"price": 99.9,
		"status": true,
		"stock": 20,
		"category": "test",
		"thumbnails": [
			"/img/1.jpg"
		]
	}
]
